[
  {
    "username": "강소라",
    "verified": false
  },
  {
    "username": "강정화",
    "verified": false
  },
  {
    "username": "고영주",
    "verified": false
  },
  {
    "username": "고영진",
    "verified": false
  },
  {
    "username": "고하은",
    "verified": false
  },
  {
    "username": "구군회",
    "verified": true
  },
  {
    "username": "구지모",
    "verified": false
  },
  {
    "username": "구해모",
    "verified": true
  },
  {
    "username": "김강돈",
    "verified": false
  },
  {
    "username": "김경곤",
    "verified": false
  },
  {
    "username": "김경환",
    "verified": true
  },
  {
    "username": "김금희",
    "verified": false
  },
  {
    "username": "김도한",
    "verified": false
  },
  {
    "username": "김미자",
    "verified": false
  },
  {
    "username": "김민경",
    "verified": false
  },
  {
    "username": "김병수",
    "verified": false
  },
  {
    "username": "김선태",
    "verified": false
  },
  {
    "username": "김송자",
    "verified": false
  },
  {
    "username": "김순옥",
    "verified": false
  },
  {
    "username": "김승단",
    "verified": false
  },
  {
    "username": "김승욱",
    "verified": false
  },
  {
    "username": "김영화",
    "verified": false
  },
  {
    "username": "김옥자",
    "verified": false
  },
  {
    "username": "김용천",
    "verified": true
  },
  {
    "username": "김원각",
    "verified": false
  },
  {
    "username": "김유경",
    "verified": false
  },
  {
    "username": "김윤성",
    "verified": false
  },
  {
    "username": "김종숙",
    "verified": false
  },
  {
    "username": "김주형",
    "verified": true
  },
  {
    "username": "김주희",
    "verified": false
  },
  {
    "username": "김철현",
    "verified": true
  },
  {
    "username": "김향란",
    "verified": false
  },
  {
    "username": "김현정",
    "verified": false
  },
  {
    "username": "김홍운",
    "verified": true
  },
  {
    "username": "나성운",
    "verified": false
  },
  {
    "username": "나성윤",
    "verified": false
  },
  {
    "username": "문경숙",
    "verified": false
  },
  {
    "username": "문안순",
    "verified": false
  },
  {
    "username": "박영환",
    "verified": true
  },
  {
    "username": "박재은",
    "verified": false
  },
  {
    "username": "박정훈",
    "verified": true
  },
  {
    "username": "박현승",
    "verified": false
  },
  {
    "username": "배성민",
    "verified": true
  },
  {
    "username": "범영근",
    "verified": true
  },
  {
    "username": "석정숙",
    "verified": false
  },
  {
    "username": "손경운",
    "verified": false
  },
  {
    "username": "손경혜",
    "verified": false
  },
  {
    "username": "손세현",
    "verified": false
  },
  {
    "username": "손일태",
    "verified": false
  },
  {
    "username": "송보라",
    "verified": false
  },
  {
    "username": "송자연",
    "verified": false
  },
  {
    "username": "신성희",
    "verified": false
  },
  {
    "username": "신재일",
    "verified": false
  },
  {
    "username": "염영숙",
    "verified": false
  },
  {
    "username": "염영옥",
    "verified": false
  },
  {
    "username": "오기쁨",
    "verified": false
  },
  {
    "username": "원세미",
    "verified": false
  },
  {
    "username": "유병숙",
    "verified": false
  },
  {
    "username": "유순금",
    "verified": false
  },
  {
    "username": "유예원",
    "verified": false
  },
  {
    "username": "유정숙",
    "verified": false
  },
  {
    "username": "윤정순",
    "verified": false
  },
  {
    "username": "윤혜리",
    "verified": false
  },
  {
    "username": "이기성",
    "verified": false
  },
  {
    "username": "이기화",
    "verified": true
  },
  {
    "username": "이범준",
    "verified": true
  },
  {
    "username": "이비선",
    "verified": false
  },
  {
    "username": "이선자",
    "verified": false
  },
  {
    "username": "이영희",
    "verified": false
  },
  {
    "username": "이은송",
    "verified": false
  },
  {
    "username": "이정숙",
    "verified": false
  },
  {
    "username": "이정희",
    "verified": false
  },
  {
    "username": "이중민",
    "verified": false
  },
  {
    "username": "이중휘",
    "verified": false
  },
  {
    "username": "이창희",
    "verified": false
  },
  {
    "username": "임지영",
    "verified": false
  },
  {
    "username": "임혜자",
    "verified": false
  },
  {
    "username": "장용호",
    "verified": false
  },
  {
    "username": "전동혁",
    "verified": true
  },
  {
    "username": "전수지",
    "verified": false
  },
  {
    "username": "정경선",
    "verified": false
  },
  {
    "username": "정명진",
    "verified": false
  },
  {
    "username": "정민우",
    "verified": true
  },
  {
    "username": "정아현",
    "verified": false
  },
  {
    "username": "정완자",
    "verified": false
  },
  {
    "username": "정음표",
    "verified": false
  },
  {
    "username": "정재원",
    "verified": false
  },
  {
    "username": "정찬민",
    "verified": false
  },
  {
    "username": "조건화",
    "verified": false
  },
  {
    "username": "조만제",
    "verified": false
  },
  {
    "username": "조민석",
    "verified": false
  },
  {
    "username": "조세희",
    "verified": false
  },
  {
    "username": "조우빈",
    "verified": false
  },
  {
    "username": "조정두",
    "verified": false
  },
  {
    "username": "조정화",
    "verified": true
  },
  {
    "username": "조하빈",
    "verified": false
  },
  {
    "username": "조현숙",
    "verified": false
  },
  {
    "username": "차태훈",
    "verified": true
  },
  {
    "username": "채민석",
    "verified": false
  },
  {
    "username": "채원숙",
    "verified": false
  },
  {
    "username": "최금숙",
    "verified": false
  },
  {
    "username": "최수현",
    "verified": false
  },
  {
    "username": "최예은",
    "verified": false
  },
  {
    "username": "최지연",
    "verified": true
  },
  {
    "username": "추영례",
    "verified": false
  },
  {
    "username": "칸리나",
    "verified": false
  },
  {
    "username": "함빈",
    "verified": false
  },
  {
    "username": "허상철",
    "verified": true
  },
  {
    "username": "홍준호",
    "verified": true
  },
  {
    "username": "황금자",
    "verified": false
  },
  {
    "username": "황수천",
    "verified": false
  },
  {
    "username": "황인혜",
    "verified": false
  }
]
